gotya_text_anonymizer/__init__.py
gotya_text_anonymizer/anonymizer.py
gotya_text_anonymizer-1.1.8.dist-info/METADATA
gotya_text_anonymizer-1.1.8.dist-info/WHEEL
gotya_text_anonymizer-1.1.8.dist-info/top_level.txt
gotya_text_anonymizer-1.1.8.dist-info/RECORD
