Metadata-Version: 2.1
Name: gotya-text-anonymizer
Version: 1.1.8
Summary: A text anonymizer to redact sensitive information
Author: Gotya Tech
Author-email: technical.team@gotya.tech
Classifier: Development Status :: 2 - Pre-Alpha
Classifier: Intended Audience :: Developers
Classifier: Programming Language :: Python :: 3.10
Requires-Dist: transformers
